SexyThumbnailGenerator/__init__.py
SexyThumbnailGenerator/classifier.py
SexyThumbnailGenerator/detector.py
SexyThumbnailGenerator/detector_utils.py
SexyThumbnailGenerator/image_utils.py
SexyThumbnailGenerator/lite_classifier.py
SexyThumbnailGenerator/thumbnails.py
SexyThumbnailGenerator/video_utils.py
SexyThumbnailGenerator/nudenet/__init__.py
SexyThumbnailGenerator/nudenet/classifier.py
SexyThumbnailGenerator/nudenet/detector.py
SexyThumbnailGenerator/nudenet/detector_utils.py
SexyThumbnailGenerator/nudenet/image_utils.py
SexyThumbnailGenerator/nudenet/lite_classifier.py
SexyThumbnailGenerator/nudenet/video_utils.py
SexyThumbnailGenerator-1.0.8.dist-info/LICENCE
SexyThumbnailGenerator-1.0.8.dist-info/METADATA
SexyThumbnailGenerator-1.0.8.dist-info/WHEEL
SexyThumbnailGenerator-1.0.8.dist-info/top_level.txt
SexyThumbnailGenerator-1.0.8.dist-info/RECORD
