Metadata-Version: 2.1
Name: SexyThumbnailGenerator
Version: 1.0.8
Summary: Generates a thumbnail from an NSFW video.
Home-page: https://aryankothari.dev/
Author: thearyadev
Author-email: aryan@aryankothari.dev
License: UNKNOWN
Platform: UNKNOWN
Classifier: Programming Language :: Python :: 3.8
Classifier: License :: OSI Approved :: MIT License
Classifier: Operating System :: OS Independent
Requires-Python: ==3.8.7
License-File: LICENCE
